memory_cache/__init__.py
memory_cache-1.0.0.dist-info/LICENSE
memory_cache-1.0.0.dist-info/METADATA
memory_cache-1.0.0.dist-info/WHEEL
memory_cache-1.0.0.dist-info/top_level.txt
memory_cache-1.0.0.dist-info/RECORD
